anyDiceSimulator/__init__.py
anyDiceSimulator/dieclasses.py
anyDiceSimulator/myfunctions.py
Any_Dice_Simulator-0.0.1.dist-info/METADATA
Any_Dice_Simulator-0.0.1.dist-info/WHEEL
Any_Dice_Simulator-0.0.1.dist-info/top_level.txt
Any_Dice_Simulator-0.0.1.dist-info/RECORD
