Metadata-Version: 2.1
Name: Any-Dice-Simulator
Version: 0.0.1
Summary: Python library to roll dice!
Author: Saksham Gupta
Author-email: Saksham Gupta <gupta.saksham98@gmail.com>
License: MIT
Project-URL: Homepage, https://github.com/pypa/sampleproject
Classifier: Programming Language :: Python :: 3
Classifier: License :: OSI Approved :: MIT License
Classifier: Operating System :: OS Independent
Requires-Python: >=3
